xia_synchronizer/__init__.py
xia_synchronizer/synchronizer.cpython-310-darwin.so
xia_synchronizer-0.0.7.dist-info/LICENSE.txt
xia_synchronizer-0.0.7.dist-info/METADATA
xia_synchronizer-0.0.7.dist-info/WHEEL
xia_synchronizer-0.0.7.dist-info/top_level.txt
xia_synchronizer-0.0.7.dist-info/RECORD
